pyg90alarm/__init__.py
pyg90alarm/alarm.py
pyg90alarm/callback.py
pyg90alarm/const.py
pyg90alarm/event_mapping.py
pyg90alarm/exceptions.py
pyg90alarm/py.typed
pyg90alarm/cloud/__init__.py
pyg90alarm/cloud/const.py
pyg90alarm/cloud/messages.py
pyg90alarm/cloud/notifications.py
pyg90alarm/cloud/protocol.py
pyg90alarm/definitions/__init__.py
pyg90alarm/definitions/base.py
pyg90alarm/definitions/devices.py
pyg90alarm/definitions/sensors.py
pyg90alarm/entities/__init__.py
pyg90alarm/entities/base_entity.py
pyg90alarm/entities/base_list.py
pyg90alarm/entities/device.py
pyg90alarm/entities/device_list.py
pyg90alarm/entities/sensor.py
pyg90alarm/entities/sensor_list.py
pyg90alarm/local/__init__.py
pyg90alarm/local/alarm_phones.py
pyg90alarm/local/alert_config.py
pyg90alarm/local/base_cmd.py
pyg90alarm/local/config.py
pyg90alarm/local/dataclass_load_save.py
pyg90alarm/local/discovery.py
pyg90alarm/local/history.py
pyg90alarm/local/host_config.py
pyg90alarm/local/host_info.py
pyg90alarm/local/host_status.py
pyg90alarm/local/net_config.py
pyg90alarm/local/notifications.py
pyg90alarm/local/paginated_cmd.py
pyg90alarm/local/paginated_result.py
pyg90alarm/local/targeted_discovery.py
pyg90alarm/local/user_data_crc.py
pyg90alarm/notifications/__init__.py
pyg90alarm/notifications/base.py
pyg90alarm/notifications/protocol.py
pyg90alarm-2.4.2.dist-info/licenses/LICENSE
pyg90alarm-2.4.2.dist-info/METADATA
pyg90alarm-2.4.2.dist-info/WHEEL
pyg90alarm-2.4.2.dist-info/top_level.txt
pyg90alarm-2.4.2.dist-info/RECORD
